multi_loras/__init__.py
multi_loras/__main__.py
multi_loras/__version__.py
multi_loras/dare.py
multi_loras/delta_weights.py
multi_loras/extract_lora.py
multi_loras/lorahub.py
multi_loras/merge_models.py
multi_loras/merge_peft_adapters.py
multi_loras/merging_methods.py
multi_loras/orthogonal_component.py
multi_loras/slora/__init__.py
multi_loras/slora/install_slora_kernel.py
multi_loras/slora/io_struct.py
multi_loras/slora/sampling_params.py
multi_loras/slora/slora_server.py
multi_loras/slora/common/__init__.py
multi_loras/slora/common/build_utils.py
multi_loras/slora/common/gqa_mem_manager.py
multi_loras/slora/common/infer_utils.py
multi_loras/slora/common/int8kv_mem_manager.py
multi_loras/slora/common/mem_allocator.py
multi_loras/slora/common/mem_manager.py
multi_loras/slora/common/ppl_int8kv_mem_manager.py
multi_loras/slora/common/basemodel/__init__.py
multi_loras/slora/common/basemodel/basemodel.py
multi_loras/slora/common/basemodel/infer_struct.py
multi_loras/slora/common/basemodel/layer_infer/__init__.py
multi_loras/slora/common/basemodel/layer_infer/base_layer_infer.py
multi_loras/slora/common/basemodel/layer_infer/post_layer_infer.py
multi_loras/slora/common/basemodel/layer_infer/pre_layer_infer.py
multi_loras/slora/common/basemodel/layer_infer/transformer_layer_infer.py
multi_loras/slora/common/basemodel/layer_infer/template/__init__.py
multi_loras/slora/common/basemodel/layer_infer/template/post_layer_infer_template.py
multi_loras/slora/common/basemodel/layer_infer/template/pre_layer_infer_template.py
multi_loras/slora/common/basemodel/layer_infer/template/transformer_layer_infer_template.py
multi_loras/slora/common/basemodel/layer_weights/__init__.py
multi_loras/slora/common/basemodel/layer_weights/base_layer_weight.py
multi_loras/slora/common/basemodel/layer_weights/hf_load_utils.py
multi_loras/slora/common/basemodel/layer_weights/pre_and_post_layer_weight.py
multi_loras/slora/common/basemodel/layer_weights/transformer_layer_weight.py
multi_loras-0.3.0.dist-info/LICENSE
multi_loras-0.3.0.dist-info/METADATA
multi_loras-0.3.0.dist-info/WHEEL
multi_loras-0.3.0.dist-info/top_level.txt
multi_loras-0.3.0.dist-info/RECORD
