Metadata-Version: 2.1
Name: multi-loras
Version: 0.3.0
Summary: Multi-LoRAs is a LLM toolkit that can simultaneously load multiple LoRA modules and automatically switch to the appropriate combination of LoRA modules based on user queries to generate the best answer. It includes tools such as extracting LoRA modules from efficiently parameters fine-tuning models, merging base models with LoRA models, and routing multiple LoRA models.
Home-page: https://github.com/uukuguy/multi_loras
Author: Jiangwen Su
Author-email: uukuguy@gmail.com
License: MIT
Classifier: Intended Audience :: Developers
Classifier: License :: OSI Approved :: MIT License
Classifier: Operating System :: OS Independent
Classifier: Programming Language :: Python :: 3
Classifier: Programming Language :: Python :: 3.8
Classifier: Programming Language :: Python :: 3.9
Classifier: Programming Language :: Python :: 3.10
Classifier: Topic :: Scientific/Engineering :: Artificial Intelligence
Requires-Python: >=3.8.0
License-File: LICENSE
Requires-Dist: tqdm >=4.27
Requires-Dist: transformers >=4.34.0
Requires-Dist: rich
